repertorio/__init__.py
repertorio/repertorio.py
repertorio-0.0.2.dist-info/AUTHORS.rst
repertorio-0.0.2.dist-info/LICENSE
repertorio-0.0.2.dist-info/METADATA
repertorio-0.0.2.dist-info/WHEEL
repertorio-0.0.2.dist-info/top_level.txt
repertorio-0.0.2.dist-info/RECORD
