Metadata-Version: 2.1
Name: repertorio
Version: 0.0.2
Summary: A setlist.fm API wrapper.
Home-page: https://github.com/jtmolon/repertorio
Author: Joao Molon
Author-email: jtmolon@gmail.com
License: MIT license': 'License :: OSI Approved :: MIT License
Keywords: repertorio setlist set list setlistfm setlist.fm
Platform: UNKNOWN
Classifier: Development Status :: 2 - Pre-Alpha
Classifier: Intended Audience :: Developers
Classifier: License :: OSI Approved :: MIT License
Classifier: Natural Language :: English
Classifier: Programming Language :: Python :: 3.7
License-File: LICENSE
License-File: AUTHORS.rst
Requires-Dist: requests
